hpfeeds/__init__.py
hpfeeds/client.py
hpfeeds/exceptions.py
hpfeeds/protocol.py
hpfeeds/asyncio/__init__.py
hpfeeds/asyncio/client.py
hpfeeds/asyncio/protocol.py
hpfeeds/blocking/__init__.py
hpfeeds/blocking/protocol.py
hpfeeds/blocking/queue.py
hpfeeds/blocking/reactor.py
hpfeeds/blocking/session.py
hpfeeds/broker/__init__.py
hpfeeds/broker/connection.py
hpfeeds/broker/prometheus.py
hpfeeds/broker/server.py
hpfeeds/broker/auth/__init__.py
hpfeeds/broker/auth/database.py
hpfeeds/broker/auth/env.py
hpfeeds/broker/auth/json.py
hpfeeds/broker/auth/memory.py
hpfeeds/broker/auth/mongo.py
hpfeeds/broker/auth/multi.py
hpfeeds/broker/auth/sqlite.py
hpfeeds/broker/utils/__init__.py
hpfeeds/broker/utils/inotify.py
hpfeeds/broker/utils/supervisor.py
hpfeeds/scripts/__init__.py
hpfeeds/scripts/broker.py
hpfeeds/scripts/cli.py
hpfeeds/twisted/__init__.py
hpfeeds/twisted/factory.py
hpfeeds/twisted/protocol.py
hpfeeds/twisted/service.py
tests/__init__.py
tests/conftest.py
tests/fakebroker.py
tests/test_asyncio_client.py
tests/test_asyncio_protocol.py
tests/test_blocking_protocol.py
tests/test_blocking_queue.py
tests/test_blocking_session.py
tests/test_broker_auth_databases.py
tests/test_broker_auth_env.py
tests/test_broker_auth_sqlite.py
tests/test_broker_connection.py
tests/test_broker_prometheus.py
tests/test_client_integration.py
tests/test_client_integration_py2.py
tests/test_protocol.py
tests/test_twisted_factory.py
tests/test_twisted_protocol.py
tests/test_twisted_service.py
tests/test_twisted_service_py2.py
tests/utils.py
hpfeeds-3.1.0.dist-info/LICENSE
hpfeeds-3.1.0.dist-info/METADATA
hpfeeds-3.1.0.dist-info/WHEEL
hpfeeds-3.1.0.dist-info/entry_points.txt
hpfeeds-3.1.0.dist-info/top_level.txt
hpfeeds-3.1.0.dist-info/RECORD
